{
  "Version": "10.0.19041.1-AMD64",
  "md5": "3e239ab691f85b6d336f501cd6e3622e",
  "imphash": "3e239ab691f85b6d336f501cd6e3622e",
  "InternalName": "mciseq",
  "CompanyName": "Microsoft Corporation",
  "FileDescription": "MCI driver for MIDI sequencer",
  "FileVersion": "10.0.19041.1 (WinBuild.160101.0800)",
  "ProductVersion": "10.0.19041.1",
  "PeChecksum": 51867,
  "Size": 31232,
  "Machine": "AMD64",
  "exports": [
    {
      "ordinal": 1,
      "name": "DriverProc"
    }
  ]
}