{
  "Version": "6.0.6000.16386-I386",
  "md5": "b928f72b051b7f2803717e75d258f087",
  "imphash": "b928f72b051b7f2803717e75d258f087",
  "InternalName": "MSSIP32 Forwarder DLL",
  "CompanyName": "Microsoft Corporation",
  "FileDescription": "MSSIP32 Forwarder DLL",
  "FileVersion": "6.0.6000.16386 (vista_rtm.061101-2205)",
  "ProductVersion": "6.0.6000.16386",
  "PeChecksum": 25877,
  "Size": 7680,
  "Machine": "I386",
  "exports": [
    {
      "ordinal": 3,
      "name": "CryptSIPCreateIndirectData"
    },
    {
      "ordinal": 1,
      "name": "CryptSIPGetInfo"
    },
    {
      "ordinal": 2,
      "name": "CryptSIPGetRegWorkingFlags"
    },
    {
      "ordinal": 4,
      "name": "CryptSIPGetSignedDataMsg"
    },
    {
      "ordinal": 5,
      "name": "CryptSIPPutSignedDataMsg"
    },
    {
      "ordinal": 6,
      "name": "CryptSIPRemoveSignedDataMsg"
    },
    {
      "ordinal": 7,
      "name": "CryptSIPVerifyIndirectData"
    },
    {
      "ordinal": 8,
      "name": "DllRegisterServer"
    },
    {
      "ordinal": 9,
      "name": "DllUnregisterServer"
    }
  ]
}