{
  "Version": "11.0.6001.7000-I386",
  "md5": "af322cbdedaea007676f1708cd6ea686",
  "imphash": "af322cbdedaea007676f1708cd6ea686",
  "InternalName": "qasf.dll",
  "CompanyName": "Microsoft Corporation",
  "FileDescription": "DirectShow ASF Support",
  "FileVersion": "11.0.6001.7000 (longhorn_rtm.080118-1840)",
  "ProductVersion": "11.0.6001.7000",
  "PeChecksum": 238983,
  "Size": 208896,
  "Machine": "I386",
  "exports": [
    {
      "ordinal": 1,
      "name": "DllCanUnloadNow"
    },
    {
      "ordinal": 2,
      "name": "DllGetClassObject"
    },
    {
      "ordinal": 3,
      "name": "DllRegisterServer"
    },
    {
      "ordinal": 4,
      "name": "DllUnregisterServer"
    }
  ]
}