{
  "Version": "7.9.9600.16384-I386",
  "md5": "f6f6207816d044dddbcbdb3791359b09",
  "imphash": "f6f6207816d044dddbcbdb3791359b09",
  "InternalName": "wuapi.dll",
  "CompanyName": "Microsoft Corporation",
  "FileDescription": "Windows Update Client API",
  "FileVersion": "7.9.9600.16384 (winblue_rtm.130821-1623)",
  "ProductVersion": "7.9.9600.16384",
  "PeChecksum": 666761,
  "Size": 659968,
  "Machine": "I386",
  "exports": [
    {
      "ordinal": 1,
      "name": null
    },
    {
      "ordinal": 2,
      "name": "DllCanUnloadNow"
    },
    {
      "ordinal": 3,
      "name": "DllGetClassObject"
    },
    {
      "ordinal": 4,
      "name": "DllRegisterServer"
    },
    {
      "ordinal": 5,
      "name": "DllUnregisterServer"
    }
  ]
}