{
  "Version": "10.0.26100.7920-AMD64",
  "md5": "9f752522eed82a5157049b471dd64d01",
  "imphash": "9f752522eed82a5157049b471dd64d01",
  "InternalName": "directmanipulation.dll",
  "CompanyName": "Microsoft Corporation",
  "FileDescription": "Microsoft Direct Manipulation Component",
  "FileVersion": "10.0.26100.7920 (WinBuild.160101.0800)",
  "ProductVersion": "10.0.26100.7920",
  "PeChecksum": 695580,
  "Size": 675024,
  "Machine": "AMD64",
  "exports": [
    {
      "ordinal": 1,
      "name": "InitializeDManipHook"
    },
    {
      "ordinal": 2,
      "name": "DllCanUnloadNow"
    },
    {
      "ordinal": 3,
      "name": "DllGetActivationFactory"
    },
    {
      "ordinal": 4,
      "name": "DllGetClassObject"
    }
  ]
}