{
  "Version": "6.1.7600.16385-I386",
  "md5": "1c0362308b40911b9069cb979cb73394",
  "imphash": "1c0362308b40911b9069cb979cb73394",
  "InternalName": "JOY.CPL",
  "CompanyName": "Microsoft Corporation",
  "FileDescription": "Game Controllers Control Panel Applet",
  "FileVersion": "6.1.7600.16385 (win7_rtm.090713-1255)",
  "ProductVersion": "6.1.7600.16385",
  "PeChecksum": 159046,
  "Size": 138240,
  "Machine": "I386",
  "exports": [
    {
      "ordinal": 1,
      "name": "CPlApplet"
    },
    {
      "ordinal": 2,
      "name": "ShowJoyCPL"
    }
  ]
}