{
  "Version": "6.1.7600.16385-I386",
  "md5": "ba54a966f873b043fdfcda0b77937855",
  "imphash": "ba54a966f873b043fdfcda0b77937855",
  "InternalName": "mgmtapi.dll",
  "CompanyName": "Microsoft Corporation",
  "FileDescription": "Microsoft SNMP Manager API (uses WinSNMP)",
  "FileVersion": "6.1.7600.16385 (win7_rtm.090713-1255)",
  "ProductVersion": "6.1.7600.16385",
  "PeChecksum": 58821,
  "Size": 18944,
  "Machine": "I386",
  "exports": [
    {
      "ordinal": 1,
      "name": "SnmpMgrClose"
    },
    {
      "ordinal": 2,
      "name": "SnmpMgrCtl"
    },
    {
      "ordinal": 3,
      "name": "SnmpMgrGetTrap"
    },
    {
      "ordinal": 4,
      "name": "SnmpMgrGetTrapEx"
    },
    {
      "ordinal": 5,
      "name": "SnmpMgrOidToStr"
    },
    {
      "ordinal": 6,
      "name": "SnmpMgrOpen"
    },
    {
      "ordinal": 7,
      "name": "SnmpMgrRequest"
    },
    {
      "ordinal": 8,
      "name": "SnmpMgrStrToOid"
    },
    {
      "ordinal": 9,
      "name": "SnmpMgrTrapListen"
    }
  ]
}